infodeslib/__init__.py
infodeslib/dcs/__init__.py
infodeslib/dcs/lca.py
infodeslib/dcs/mla.py
infodeslib/dcs/ola.py
infodeslib/dcs/rank.py
infodeslib/dcs/util/__init__.py
infodeslib/dcs/util/diversity.py
infodeslib/dcs/util/utils.py
infodeslib/des/__init__.py
infodeslib/des/base.py
infodeslib/des/desknn.py
infodeslib/des/desp.py
infodeslib/des/knop.py
infodeslib/des/knorae.py
infodeslib/des/knorae_w.py
infodeslib/des/knorau.py
infodeslib/des/knorau_w.py
infodeslib/des/util/__init__.py
infodeslib/des/util/diversity.py
infodeslib/des/util/utils.py
infodeslib-0.1.4.dist-info/METADATA
infodeslib-0.1.4.dist-info/WHEEL
infodeslib-0.1.4.dist-info/top_level.txt
infodeslib-0.1.4.dist-info/RECORD
