Metadata-Version: 2.1
Name: infodeslib
Version: 0.1.4
Summary: Implementation of Dynamic Ensemble Selection methods with Late Fusion
Home-page: https://github.com/adv-panda/infodeslib
Author: adv-panda
Author-email: panda@gmail.com
Classifier: Programming Language :: Python :: 3
Classifier: License :: OSI Approved :: MIT License
Classifier: Operating System :: OS Independent
Requires-Python: >=3.7
